sub20/__init__.py
sub20/_errors.py
sub20/device.py
sub20/ctypeslib/__init__.py
sub20/ctypeslib/libsub.py
sub20/ctypeslib/utils.py
pysub20-0.0.2.dist-info/METADATA
pysub20-0.0.2.dist-info/WHEEL
pysub20-0.0.2.dist-info/licenses/AUTHORS
pysub20-0.0.2.dist-info/licenses/LICENSE
pysub20-0.0.2.dist-info/RECORD
