Metadata-Version: 2.1
Name: pysub20
Version: 0.0.2
Summary: Python wrapper around XDIMAX SUB-20 library
Project-URL: Documentation, http://www.xdimax.com/sub20/sub20.html
Project-URL: Homepage, https://github.com/paulgr2008/pysub20
Project-URL: Source, https://github.com/paulgr2008/pysub20
Author-email: Paul Grebeniuk <paul@coolautomation.com>
License-File: AUTHORS
License-File: LICENSE
Keywords: utility
Classifier: Development Status :: 4 - Beta
Classifier: Intended Audience :: Developers
Classifier: License :: OSI Approved :: GNU Lesser General Public License v2 or later (LGPLv2+)
Classifier: Operating System :: Microsoft :: Windows
Classifier: Operating System :: POSIX
Classifier: Programming Language :: Python :: 3
Classifier: Programming Language :: Python :: 3.6
Classifier: Programming Language :: Python :: 3.7
Classifier: Programming Language :: Python :: 3.8
Classifier: Programming Language :: Python :: 3.9
Classifier: Programming Language :: Python :: 3.10
Classifier: Programming Language :: Python :: Implementation :: CPython
Classifier: Programming Language :: Python :: Implementation :: PyPy
Classifier: Topic :: Communications
Requires-Python: >=3.6.*
